pywebscrapr/__init__.py
pywebscrapr-0.1.6.dist-info/licenses/LICENSE
pywebscrapr-0.1.6.dist-info/METADATA
pywebscrapr-0.1.6.dist-info/WHEEL
pywebscrapr-0.1.6.dist-info/top_level.txt
pywebscrapr-0.1.6.dist-info/RECORD
